<persistence xmlns="http://xmlns.jcp.org/xml/ns/persistence"
             xmlns:xsi="http://www.w3.org/2001/XMLSchema-instance"
             xsi:schemaLocation="http://xmlns.jcp.org/xml/ns/persistence
                                 http://xmlns.jcp.org/xml/ns/persistence/persistence_2_1.xsd"
             version="2.1">

    <!--
      - This is a standard persistence.xml used to configure a JPA provider.
      - For details, see the Hibernate ORM documentation:
      - http://docs.jboss.org/hibernate/orm/5.2/userguide/html_single/Hibernate_User_Guide.html#bootstrap-jpa
      -->
    <persistence-unit name="default" transaction-type="RESOURCE_LOCAL">
        <provider>org.hibernate.jpa.HibernatePersistenceProvider</provider>
        <non-jta-data-source>DefaultDS</non-jta-data-source>
        <properties>
            <property name="hibernate.dialect" value="org.hibernate.dialect.H2Dialect"/>
        </properties>
    </persistence-unit>

</persistence>
